_atoti_server_gcp/__init__.py
_atoti_server_gcp/__resources__/plugin.jar
_atoti_server_gcp/_plugin.py
_atoti_server_gcp/_resources_directory.py
_atoti_server_gcp/py.typed
atoti_server_gcp-0.9.12.dist-info/WHEEL
atoti_server_gcp-0.9.12.dist-info/entry_points.txt
atoti_server_gcp-0.9.12.dist-info/METADATA
atoti_server_gcp-0.9.12.dist-info/RECORD
