Metadata-Version: 2.3
Name: atoti-server-gcp
Version: 0.9.12
Summary: Resources to interact with Google Cloud Platform
Author: ActiveViam
Author-email: ActiveViam <atoti-dev@activeviam.com>
Classifier: Development Status :: 4 - Beta
Classifier: License :: Free for non-commercial use
Classifier: Operating System :: OS Independent
Classifier: Programming Language :: Java
Classifier: Programming Language :: Python :: 3
Classifier: Typing :: Typed
Requires-Dist: atoti-core==0.9.12
Requires-Dist: typing-extensions>=4.15.0
Requires-Python: >=3.10
Project-URL: Homepage, https://www.atoti.io
Project-URL: Issues, https://github.com/atoti/atoti/issues
